ezserialization/__init__.py
ezserialization/_serialization.py
ezserialization/py.typed
ezserialization-0.5.3.dist-info/LICENSE
ezserialization-0.5.3.dist-info/METADATA
ezserialization-0.5.3.dist-info/WHEEL
ezserialization-0.5.3.dist-info/RECORD
