Metadata-Version: 2.3
Name: ezserialization
Version: 0.5.3
Summary: Simple, easy to use & transparent python objects serialization & deserialization.
License: MIT
Author: Matas Gumbinas
Author-email: matas.gumbinas@gmail.com
Requires-Python: >=3.10,<4.0
Classifier: License :: OSI Approved :: MIT License
Classifier: Programming Language :: Python :: 3
Classifier: Programming Language :: Python :: 3.10
Classifier: Programming Language :: Python :: 3.11
Classifier: Programming Language :: Python :: 3.12
Classifier: Programming Language :: Python :: 3.13
